main.py
task_4_nohomo-1.0.0.dist-info/METADATA
task_4_nohomo-1.0.0.dist-info/WHEEL
task_4_nohomo-1.0.0.dist-info/top_level.txt
task_4_nohomo-1.0.0.dist-info/RECORD
