Metadata-Version: 2.1
Name: task_4_nohomo
Version: 1.0.0
Summary: task_4
Author-email: Victor <logday2017@gmail.com>
Requires-Python: >=3.6
